brancher/__init__.py
brancher/config.py
brancher/distributions.py
brancher/functions.py
brancher/geometric_ranges.py
brancher/gradient_estimators.py
brancher/inference.py
brancher/modules.py
brancher/optimizers.py
brancher/pandas_interface.py
brancher/particle_inference_tools.py
brancher/standard_variables.py
brancher/stochastic_processes.py
brancher/time_series_models.py
brancher/transformations.py
brancher/utilities.py
brancher/variables.py
brancher/visualizations.py
brancher-0.3.5.dist-info/LICENSE
brancher-0.3.5.dist-info/METADATA
brancher-0.3.5.dist-info/WHEEL
brancher-0.3.5.dist-info/top_level.txt
brancher-0.3.5.dist-info/RECORD
