Metadata-Version: 2.1
Name: brancher
Version: 0.3.5
Summary: A user-centered Python package for differentiable probabilistic inference
Home-page: https://brancher.org/
Author: Brancher development team
Author-email: info@brancher.org
License: MIT
Platform: UNKNOWN
Classifier: Programming Language :: Python :: 3
Classifier: License :: OSI Approved :: MIT License
Classifier: Operating System :: OS Independent
Requires-Dist: python-version (>="3.7")
Requires-Dist: numpy (>=1.15.4)
Requires-Dist: pandas (>=0.23.4)
Requires-Dist: matplotlib (>=3.0.2)
Requires-Dist: seaborn (>=0.9.0)
Requires-Dist: scipy (>=1.1.0)
Requires-Dist: tqdm (>=4.28.1)
